README.rst
setup.py
src/pyunrawmodule-9.28.c
src/pyunraw/__init__.py
src/pyunraw/pyunraw.py
src/pyunraw.egg-info/PKG-INFO
src/pyunraw.egg-info/SOURCES.txt
src/pyunraw.egg-info/dependency_links.txt
src/pyunraw.egg-info/top_level.txt