Metadata-Version: 1.1
Name: pyunraw
Version: 1.2.0
Summary: A CPython implementation of dcraw
Home-page: https://launchpad.net/pyunraw
Author: Vincent Vande Vyvre
Author-email: vincent.vandevyvre@oqapy.eu
License: GPL-3
Keywords: raw image dcraw digital photo
Platform: UNKNOWN
Classifier: Development Status :: 5 - Production/Stable
Classifier: Intended Audience :: Developers
Classifier: Topic :: Multimedia :: Graphics
Classifier: License :: OSI Approved :: GNU General Public License v3 (GPLv3)
Classifier: Programming Language :: C
Classifier: Programming Language :: Python :: 3.4
Classifier: Programming Language :: Python :: 3.5
Classifier: Programming Language :: Python :: 3.6
Classifier: Programming Language :: Python :: 3.7
Classifier: Programming Language :: Python :: Implementation :: CPython
